[{"state": "01", "income": "64.31"}, {"state": "02", "income": "89.23"}, {"state": "04", "income": "84.43"}, {"state": "05", "income": "67.08"}, {"state": "06", "income": "110.5"}, {"state": "08", "income": "93.81"}, {"state": "09", "income": "88.27"}, {"state": "10", "income": "71.36"}, {"state": "11", "income": "128.35"}, {"state": "12", "income": "93.81"}, {"state": "13", "income": "73.19"}, {"state": "15", "income": "107.64"}, {"state": "16", "income": "75.1"}, {"state": "17", "income": "77.11"}, {"state": "18", "income": "61.98"}, {"state": "19", "income": "64.35"}, {"state": "20", "income": "64.31"}, {"state": "21", "income": "61.02"}, {"state": "22", "income": "75.13"}, {"state": "23", "income": "61.25"}, {"state": "24", "income": "87.77"}, {"state": "25", "income": "88.43"}, {"state": "26", "income": "61.76"}, {"state": "27", "income": "77.85"}, {"state": "28", "income": "71.5"}, {"state": "29", "income": "63.98"}, {"state": "30", "income": "73.24"}, {"state": "31", "income": "65.37"}, {"state": "32", "income": "101.94"}, {"state": "33", "income": "75.85"}, {"state": "34", "income": "95.57"}, {"state": "35", "income": "75.07"}, {"state": "36", "income": "85.87"}, {"state": "37", "income": "73.82"}, {"state": "38", "income": "67.08"}, {"state": "39", "income": "62.66"}, {"state": "40", "income": "71.94"}, {"state": "41", "income": "84.18"}, {"state": "42", "income": "64.74"}, {"state": "44", "income": "80.21"}, {"state": "45", "income": "77.02"}, {"state": "46", "income": "68.33"}, {"state": "47", "income": "66.85"}, {"state": "48", "income": "85.58"}, {"state": "49", "income": "94.39"}, {"state": "50", "income": "65.6"}, {"state": "51", "income": "76.07"}, {"state": "53", "income": "95.41"}, {"state": "54", "income": "57.67"}, {"state": "55", "income": "67.27"}, {"state": "56", "income": "83.6"}, {"state": "72", "income": "66.39"}]